{
  "hash": "5225c6b887b9227fa76e",
  "publicPath": "/",
  "outputPath": "/Users/sd/@dev/gatsby_apps/gatsby-gpo/public",
  "assetsByChunkName": {
    "main": [
      "render-page.js"
    ]
  },
  "assets": [
    {
      "type": "asset",
      "name": "static/thumbnail-8495e76e465026776c1f48538bb43c76.png",
      "size": 1780190,
      "emitted": false,
      "comparedForEmit": false,
      "cached": true,
      "info": {
        "immutable": true,
        "sourceFilename": "src/assets/thumbnail/thumbnail.png"
      },
      "chunkNames": [],
      "chunkIdHints": [],
      "auxiliaryChunkNames": [
        "main"
      ],
      "auxiliaryChunkIdHints": [],
      "chunks": [],
      "auxiliaryChunks": [
        179
      ]
    },
    {
      "type": "asset",
      "name": "render-page.js",
      "size": 1018036,
      "emitted": false,
      "comparedForEmit": false,
      "cached": true,
      "info": {
        "javascriptModule": false,
        "related": {
          "sourceMap": "render-page.js.map"
        }
      },
      "chunkNames": [
        "main"
      ],
      "chunkIdHints": [],
      "auxiliaryChunkNames": [],
      "auxiliaryChunkIdHints": [],
      "filteredRelated": 1,
      "chunks": [
        179
      ],
      "auxiliaryChunks": []
    },
    {
      "type": "asset",
      "name": "static/divider2Svg-121afb6665b5a59e5941af833cb096f1.svg",
      "size": 259534,
      "emitted": false,
      "comparedForEmit": false,
      "cached": true,
      "info": {
        "immutable": true,
        "sourceFilename": "src/assets/illustrations/divider2Svg.svg"
      },
      "chunkNames": [],
      "chunkIdHints": [],
      "auxiliaryChunkNames": [
        "main"
      ],
      "auxiliaryChunkIdHints": [],
      "chunks": [],
      "auxiliaryChunks": [
        179
      ]
    },
    {
      "type": "asset",
      "name": "static/semafor-ec9756db3055c92ecacc135baeb4bb04.svg",
      "size": 159567,
      "emitted": false,
      "comparedForEmit": false,
      "cached": true,
      "info": {
        "immutable": true,
        "sourceFilename": "src/assets/illustrations/semafor.svg"
      },
      "chunkNames": [],
      "chunkIdHints": [],
      "auxiliaryChunkNames": [
        "main"
      ],
      "auxiliaryChunkIdHints": [],
      "chunks": [],
      "auxiliaryChunks": [
        179
      ]
    },
    {
      "type": "asset",
      "name": "static/slider-bckg-d086eae101bbd623db6175f55862882b.webp",
      "size": 113452,
      "emitted": false,
      "comparedForEmit": false,
      "cached": true,
      "info": {
        "immutable": true,
        "sourceFilename": "src/assets/illustrations/slider-bckg.webp"
      },
      "chunkNames": [],
      "chunkIdHints": [],
      "auxiliaryChunkNames": [
        "main"
      ],
      "auxiliaryChunkIdHints": [],
      "chunks": [],
      "auxiliaryChunks": [
        179
      ]
    },
    {
      "type": "asset",
      "name": "static/divider2MobSvg-2dd46749feac53d59ea73999b0df0c8c.svg",
      "size": 99308,
      "emitted": false,
      "comparedForEmit": false,
      "cached": true,
      "info": {
        "immutable": true,
        "sourceFilename": "src/assets/illustrations/divider2MobSvg.svg"
      },
      "chunkNames": [],
      "chunkIdHints": [],
      "auxiliaryChunkNames": [
        "main"
      ],
      "auxiliaryChunkIdHints": [],
      "chunks": [],
      "auxiliaryChunks": [
        179
      ]
    },
    {
      "type": "asset",
      "name": "static/card1_img-024d119514b4abae63c623d8a91b3f42.webp",
      "size": 75182,
      "emitted": false,
      "comparedForEmit": false,
      "cached": true,
      "info": {
        "immutable": true,
        "sourceFilename": "src/assets/illustrations/card1_img.webp"
      },
      "chunkNames": [],
      "chunkIdHints": [],
      "auxiliaryChunkNames": [
        "main"
      ],
      "auxiliaryChunkIdHints": [],
      "chunks": [],
      "auxiliaryChunks": [
        179
      ]
    },
    {
      "type": "asset",
      "name": "static/tanulo_7-8c12247924d4be2e01e2543850c8e5bf.webp",
      "size": 66084,
      "emitted": false,
      "comparedForEmit": false,
      "cached": true,
      "info": {
        "immutable": true,
        "sourceFilename": "src/assets/illustrations/tanulo_7.webp"
      },
      "chunkNames": [],
      "chunkIdHints": [],
      "auxiliaryChunkNames": [
        "main"
      ],
      "auxiliaryChunkIdHints": [],
      "chunks": [],
      "auxiliaryChunks": [
        179
      ]
    },
    {
      "type": "asset",
      "name": "static/tanulo_2-a88c43c53fae449e885ee97de8710c5e.webp",
      "size": 63810,
      "emitted": false,
      "comparedForEmit": false,
      "cached": true,
      "info": {
        "immutable": true,
        "sourceFilename": "src/assets/illustrations/tanulo_2.webp"
      },
      "chunkNames": [],
      "chunkIdHints": [],
      "auxiliaryChunkNames": [
        "main"
      ],
      "auxiliaryChunkIdHints": [],
      "chunks": [],
      "auxiliaryChunks": [
        179
      ]
    },
    {
      "type": "asset",
      "name": "static/tanulo_5-c2d7236a27840c71d8b16ca3913477f8.webp",
      "size": 62230,
      "emitted": false,
      "comparedForEmit": false,
      "cached": true,
      "info": {
        "immutable": true,
        "sourceFilename": "src/assets/illustrations/tanulo_5.webp"
      },
      "chunkNames": [],
      "chunkIdHints": [],
      "auxiliaryChunkNames": [
        "main"
      ],
      "auxiliaryChunkIdHints": [],
      "chunks": [],
      "auxiliaryChunks": [
        179
      ]
    },
    {
      "type": "asset",
      "name": "static/tanulo_1-865d6d6d965e495748ce4660dd61c9ea.webp",
      "size": 47990,
      "emitted": false,
      "comparedForEmit": false,
      "cached": true,
      "info": {
        "immutable": true,
        "sourceFilename": "src/assets/illustrations/tanulo_1.webp"
      },
      "chunkNames": [],
      "chunkIdHints": [],
      "auxiliaryChunkNames": [
        "main"
      ],
      "auxiliaryChunkIdHints": [],
      "chunks": [],
      "auxiliaryChunks": [
        179
      ]
    },
    {
      "type": "asset",
      "name": "static/card2_img-3180f6306d0c6c2b1055911b39871508.webp",
      "size": 41746,
      "emitted": false,
      "comparedForEmit": false,
      "cached": true,
      "info": {
        "immutable": true,
        "sourceFilename": "src/assets/illustrations/card2_img.webp"
      },
      "chunkNames": [],
      "chunkIdHints": [],
      "auxiliaryChunkNames": [
        "main"
      ],
      "auxiliaryChunkIdHints": [],
      "chunks": [],
      "auxiliaryChunks": [
        179
      ]
    },
    {
      "type": "asset",
      "name": "static/card3_img-f75a719cab5d53afc9452036342557ca.webp",
      "size": 36938,
      "emitted": false,
      "comparedForEmit": false,
      "cached": true,
      "info": {
        "immutable": true,
        "sourceFilename": "src/assets/illustrations/card3_img.webp"
      },
      "chunkNames": [],
      "chunkIdHints": [],
      "auxiliaryChunkNames": [
        "main"
      ],
      "auxiliaryChunkIdHints": [],
      "chunks": [],
      "auxiliaryChunks": [
        179
      ]
    },
    {
      "type": "asset",
      "name": "static/tanulo_4-1cb4bad50d74b9958d923ce16618c951.webp",
      "size": 33728,
      "emitted": false,
      "comparedForEmit": false,
      "cached": true,
      "info": {
        "immutable": true,
        "sourceFilename": "src/assets/illustrations/tanulo_4.webp"
      },
      "chunkNames": [],
      "chunkIdHints": [],
      "auxiliaryChunkNames": [
        "main"
      ],
      "auxiliaryChunkIdHints": [],
      "chunks": [],
      "auxiliaryChunks": [
        179
      ]
    },
    {
      "type": "asset",
      "name": "static/tanulo_3-e960e4db063d4671fa9890a7a82e7275.webp",
      "size": 32524,
      "emitted": false,
      "comparedForEmit": false,
      "cached": true,
      "info": {
        "immutable": true,
        "sourceFilename": "src/assets/illustrations/tanulo_3.webp"
      },
      "chunkNames": [],
      "chunkIdHints": [],
      "auxiliaryChunkNames": [
        "main"
      ],
      "auxiliaryChunkIdHints": [],
      "chunks": [],
      "auxiliaryChunks": [
        179
      ]
    },
    {
      "type": "asset",
      "name": "static/tanulo_6-b400a8ad4d4f11193b8b43447a186262.webp",
      "size": 24578,
      "emitted": false,
      "comparedForEmit": false,
      "cached": true,
      "info": {
        "immutable": true,
        "sourceFilename": "src/assets/illustrations/tanulo_6.webp"
      },
      "chunkNames": [],
      "chunkIdHints": [],
      "auxiliaryChunkNames": [
        "main"
      ],
      "auxiliaryChunkIdHints": [],
      "chunks": [],
      "auxiliaryChunks": [
        179
      ]
    },
    {
      "type": "asset",
      "name": "static/hero-about-1ed04d96095270e0beb63b7591902fb9.webp",
      "size": 24044,
      "emitted": false,
      "comparedForEmit": false,
      "cached": true,
      "info": {
        "immutable": true,
        "sourceFilename": "src/assets/illustrations/hero-about.webp"
      },
      "chunkNames": [],
      "chunkIdHints": [],
      "auxiliaryChunkNames": [
        "main"
      ],
      "auxiliaryChunkIdHints": [],
      "chunks": [],
      "auxiliaryChunks": [
        179
      ]
    }
  ],
  "namedChunkGroups": {
    "main": {
      "name": "main",
      "chunks": [
        179
      ],
      "assets": [
        {
          "name": "render-page.js"
        }
      ],
      "filteredAssets": 0,
      "assetsSize": null,
      "filteredAuxiliaryAssets": 17,
      "auxiliaryAssetsSize": null,
      "children": {},
      "childAssets": {}
    }
  },
  "generator": "loadable-components",
  "chunks": [
    {
      "id": 179,
      "files": [
        "render-page.js"
      ]
    }
  ]
}